{
  "unversionedId": "Docusaurus_References/Infima Powered/infima",
  "id": "Docusaurus_References/Infima Powered/infima",
  "isDocsHomePage": false,
  "title": "Alert",
  "description": "Colors",
  "source": "@site/docs/Docusaurus_References/Infima Powered/Alert.md",
  "sourceDirName": "Docusaurus_References/Infima Powered",
  "slug": "/Docusaurus_References/Infima Powered/infima",
  "permalink": "/docs/Docusaurus_References/Infima Powered/infima",
  "editUrl": "https://github.com/shuoO-24/blog-site/tree/main/docs/docs/Docusaurus_References/Infima Powered/Alert.md",
  "version": "current",
  "frontMatter": {
    "id": "infima",
    "title": "alert"
  },
  "sidebar": "tutorialSidebar",
  "previous": {
    "title": "添加目录 Inline TOC",
    "permalink": "/docs/Docusaurus_References/Markdown_MDX/toc"
  },
  "next": {
    "title": "Nav bar usage",
    "permalink": "/docs/Docusaurus_References/Infima Powered/navbar"
  }
}